pyinkr/__init__.py
pyinkr/__main__.py
pyinkr/dialogs.py
pyinkr/main.py
pyinkr/py.typed
pyinkr/screen.py
pyinkr/style.tcss
pyinkr/widgets.py
pyinkr-0.2.0.dist-info/WHEEL
pyinkr-0.2.0.dist-info/entry_points.txt
pyinkr-0.2.0.dist-info/METADATA
pyinkr-0.2.0.dist-info/RECORD
