Metadata-Version: 2.4
Name: pyinkr
Version: 0.2.0
Summary: A tool for managing MKV files
Keywords: terminal
Author: xMohnad
License-Expression: MIT
Classifier: Environment :: Console
Classifier: Development Status :: 4 - Beta
Classifier: Operating System :: OS Independent
Classifier: Programming Language :: Python :: 3.9
Classifier: Programming Language :: Python :: 3.10
Classifier: Programming Language :: Python :: 3.11
Classifier: Programming Language :: Python :: 3.12
Classifier: Programming Language :: Python :: 3.13
Classifier: Topic :: Terminals
Classifier: Topic :: Multimedia :: Video
Classifier: Typing :: Typed
Requires-Dist: pymkv2>=2.1.1
Requires-Dist: textual>=2.1.2
Requires-Dist: textual-fspicker>=0.4.1
Requires-Python: >=3.9
Project-URL: Discussions, https://github.com/xMohnad/Inkr/discussions
Project-URL: Homepage, https://github.com/xMohnad/Inkr
Project-URL: Issues, https://github.com/xMohnad/Inkr/issues
Project-URL: Repository, https://github.com/xMohnad/Inkr
